{
  "success": true,
  "message": null,
  "requestId": "req_missing_responses_001",
  "timestamp": "2025-09-26T10:30:00.000Z",
  "data": {
    "items": [
      {
        "_id": "66fa1f5f9a8e6f0012d3c777",
        "merchant": "mrc_123",
        "channel": "chn_123",
        "question": "ما هي أسعار الشحن؟",
        "botReply": "آسف، لم أتمكن من فهم سؤالك. يمكنك إعادة صياغة السؤال أو الاتصال بخدمة العملاء.",
        "sessionId": "sess_123456",
        "aiAnalysis": "السؤال يتعلق بسياسة الشحن والتوصيل",
        "customerId": "+966501234567",
        "type": "unanswered",
        "resolved": false,
        "resolvedAt": null,
        "resolvedBy": null,
        "createdAt": "2025-09-25T14:20:00.000Z",
        "updatedAt": "2025-09-25T14:20:00.000Z"
      },
      {
        "_id": "66fa1f5f9a8e6f0012d3c888",
        "merchant": "mrc_123",
        "channel": "chn_124",
        "question": "كيف يمكنني إعادة طلبي؟",
        "botReply": null,
        "sessionId": "sess_789012",
        "aiAnalysis": "طلب معلومات عن سياسة الإرجاع والاستبدال",
        "customerId": "+966507654321",
        "type": "unclear",
        "resolved": true,
        "resolvedAt": "2025-09-25T15:30:00.000Z",
        "resolvedBy": "admin_001",
        "createdAt": "2025-09-25T14:15:00.000Z",
        "updatedAt": "2025-09-25T15:30:00.000Z"
      },
      {
        "_id": "66fa1f5f9a8e6f0012d3c999",
        "merchant": "mrc_123",
        "channel": "chn_123",
        "question": "هل لديكم لوحات شمسية؟",
        "botReply": "نعم، لدينا مجموعة متنوعة من اللوحات الشمسية بقدرات مختلفة. يمكنني مساعدتك في اختيار المناسب لاحتياجاتك.",
        "sessionId": "sess_345678",
        "aiAnalysis": "استفسار عن توفر منتج محدد",
        "customerId": "+966509876543",
        "type": "product_related",
        "resolved": true,
        "resolvedAt": "2025-09-25T14:25:00.000Z",
        "resolvedBy": "system",
        "createdAt": "2025-09-25T14:10:00.000Z",
        "updatedAt": "2025-09-25T14:25:00.000Z"
      }
    ],
    "pageInfo": {
      "nextCursor": "eyJpZCI6IjY2ZmExZjVmOWE4ZTZmMDAxMmQzYzk5OSJ9",
      "previousCursor": null,
      "hasNext": true,
      "hasPrev": false,
      "limit": 20
    }
  }
}
